Metadata-Version: 2.1
Name: moscow-test
Version: 0.0
Summary: bla-vla-bla
Home-page: UNKNOWN
Author-email: kirill.leto.kirov43@yandex.ru
License: UNKNOWN
Platform: UNKNOWN
